tcprimedapi/__init__.py
tcprimedapi/api.py
tcprimedapi-1.0b0.dist-info/LICENSE
tcprimedapi-1.0b0.dist-info/METADATA
tcprimedapi-1.0b0.dist-info/WHEEL
tcprimedapi-1.0b0.dist-info/top_level.txt
tcprimedapi-1.0b0.dist-info/RECORD
