Metadata-Version: 2.2
Name: tcprimedapi
Version: 1.0b0
Summary: An API to pull TC PRIMED files based on user requests.
Author-email: TC PRIMED Development Team <CIRA_tcprimed@colostate.edu>
License: BSD 3-Clause License
Project-URL: Homepage, https://rammb-data.cira.colostate.edu/tcprimed/
Project-URL: Repository, https://github.com/CSU-CIRA/tcprimedapi/
Keywords: tools
Classifier: Development Status :: 3 - Alpha
Classifier: Intended Audience :: Developers
Classifier: Intended Audience :: Science/Research
Classifier: License :: OSI Approved :: BSD License
Classifier: Operating System :: OS Independent
Classifier: Programming Language :: Python :: 3
Classifier: Programming Language :: Python :: 3.9
Classifier: Programming Language :: Python :: 3.10
Classifier: Programming Language :: Python :: 3.11
Classifier: Programming Language :: Python :: 3.12
Classifier: Topic :: Database :: Front-Ends
Classifier: Topic :: Internet :: WWW/HTTP :: Indexing/Search
Classifier: Topic :: Scientific/Engineering
Classifier: Topic :: Scientific/Engineering :: Artificial Intelligence
Classifier: Topic :: Scientific/Engineering :: Atmospheric Science
Classifier: Topic :: Software Development :: Libraries :: Python Modules
Requires-Python: >=3.9
License-File: LICENSE
Requires-Dist: boto3>=1.34
